<!-- Diseases Extended (© Revan© ) -->

<Root>
	<Entry>
		<zType>BONUS_EVENTOPTION_TRAIT_A_CHILL_IN_THE_PALACE_OPTION_0_CHARACTER_1</zType>
		<iDivorcedBySubject>0</iDivorcedBySubject>
		<aeAddTraits>
			<zValue>TRAIT_BUBONIC_PLAGUE</zValue>
		</aeAddTraits>
		<aeRemoveTraits>
			<zValue>TRAIT_INFLUENZA</zValue>
		</aeRemoveTraits>
	</Entry>
	<Entry>
		<zType>BONUS_EVENTOPTION_TRAIT_A_CHILL_IN_THE_PALACE_OPTION_1_CHARACTER_1</zType>
		<aeRemoveTraits>
			<zValue>TRAIT_INFLUENZA</zValue>
		</aeRemoveTraits>
	</Entry>
	<Entry>
		<zType>BONUS_EVENTOPTION_HARVEST_FILTHY_ANIMALS_OPTION_1_CHARACTER_0</zType>
		<aeRandomTrait>
			<zValue>TRAIT_INFLUENZA</zValue>
			<zValue>TRAIT_MISERABLE</zValue>
			<zValue>TRAIT_RABIES</zValue>
		</aeRandomTrait>
	</Entry>
	<Entry>
		<zType>BONUS_EVENTOPTION_TRAIT_TOO_MUCH_OF_A_GOOD_THING_OPTION_0_CHARACTER_1</zType>
		<aeRandomTrait>
			<zValue>TRAIT_SMALLPOX</zValue>
			<zValue>TRAIT_INFLUENZA</zValue>
			<zValue>TRAIT_MALARIA</zValue>
		</aeRandomTrait>
	</Entry>
	<Entry>
		<zType>BONUS_EVENTOPTION_TRAIT_TOO_MUCH_OF_A_GOOD_THING_OPTION_2_CHARACTER_1</zType>
		<aeRandomTrait>
			<zValue>TRAIT_INFLUENZA</zValue>
			<zValue>TRAIT_SMALLPOX</zValue>
			<zValue>TRAIT_MALARIA</zValue>
		</aeRandomTrait>
	</Entry>
	<Entry>
		<zType>BONUS_EVENTOPTION_WANDERING_THE_WILDERNESS_OPTION_0_CHARACTER_1</zType>
		<aeAddTraits>
			<zValue>TRAIT_MALARIA</zValue>
		</aeAddTraits>
		<aeRemoveTraits>
			<zValue>TRAIT_EXPLORING</zValue>
		</aeRemoveTraits>
		<aeBonuses>
			<zValue>BONUS_XP_CHARACTER_SMALL</zValue>
		</aeBonuses>
	</Entry>
	<Entry>
		<zType>BONUS_EVENTOPTION_TRAIT_TAKING_ITS_TOLL_OPTION_1_CHARACTER_0</zType>
		<aeAddTraits>
			<zValue>TRAIT_MALARIA</zValue>
		</aeAddTraits>
		<aeRemoveTraits>
			<zValue>TRAIT_SLIGHTED</zValue>
		</aeRemoveTraits>
	</Entry>
	<Entry>
		<zType>BONUS_EVENTOPTION_TRAIT_TAKING_ITS_TOLL_OPTION_2_CHARACTER_0</zType>
		<AddLeaderRelationship>RELATIONSHIP_INFLUENCED_BY</AddLeaderRelationship>
		<aeAddTraits>
			<zValue>TRAIT_MALARIA</zValue>
		</aeAddTraits>
	</Entry>
	<Entry>
		<zType>BONUS_EVENTOPTION_HAOMA_ILL</zType>
		<aeRemoveTraits>
			<zValue>TRAIT_MALARIA</zValue>
			<zValue>TRAIT_SMALLPOX</zValue>
			<zValue>TRAIT_TYPHOID</zValue>
			<zValue>TRAIT_INFLUENZA</zValue>
			<zValue>TRAIT_RABIES</zValue>
			<zValue>TRAIT_PNEUMONIA</zValue>
			<zValue>TRAIT_TUBERCULOSIS</zValue>
			<zValue>TRAIT_TRACHOMA</zValue>
			<zValue>TRAIT_SEVERELY_ILL</zValue>
		</aeRemoveTraits>
	</Entry>
	<Entry>
		<zType>BONUS_EVENTSTORY_THE_POX_SPREADS_CHARACTER_1</zType>
		<aeAddTraits>
			<zValue>TRAIT_SMALLPOX</zValue>
		</aeAddTraits>
	</Entry>
	<Entry>
		<zType>BONUS_EVENTOPTION_SHADOW_OF_DEATH_OPTION_0_CHARACTER_2</zType>
		<aeAddTraits>
			<zValue>TRAIT_MOURNING</zValue>
			<zValue>TRAIT_TUBERCULOSIS</zValue>
		</aeAddTraits>
	</Entry>
	<Entry>
		<zType>BONUS_EVENTOPTION_RALLY_THE_DRUNKEN_ARMY_OPTION_0_CHARACTER_1</zType>
		<aeAddTraits>
			<zValue>TRAIT_DRUNK</zValue>
			<zValue>TRAIT_PNEUMONIA</zValue>
		</aeAddTraits>
	</Entry>
	<Entry>
		<zType>BONUS_EVENTOPTION_IN_THE_WATER_OPTION_2_CHARACTER_0</zType>
		<AddLeaderRelationship>RELATIONSHIP_INFLUENCED_BY</AddLeaderRelationship>
		<aeRemoveTraits>
			<zValue>TRAIT_BUBONIC_PLAGUE</zValue>
			<zValue>TRAIT_INFLUENZA</zValue>
			<zValue>TRAIT_TYPHOID</zValue>
			<zValue>TRAIT_SEVERELY_ILL</zValue>
		</aeRemoveTraits>
	</Entry>
	<Entry>
		<zType>BONUS_EVENTOPTION_CULINARY_ESCAPADES_2</zType>
		<aeRandomTrait>
			<zValue>TRAIT_ILL</zValue>
			<zValue>TRAIT_ROBUST</zValue>
		</aeRandomTrait>
	</Entry>
	<Entry>
		<zType>BONUS_RUINS_STRANGE_MEDICINE_OPTION_HEAL_SEVERELY_ILL</zType>
		<iXPCharacter>50</iXPCharacter>
		<aeRemoveTraits>
			<zValue>TRAIT_BUBONIC_PLAGUE</zValue>
			<zValue>TRAIT_TYPHOID</zValue>
			<zValue>TRAIT_LEPROSY</zValue>
			<zValue>TRAIT_PNEUMONIA</zValue>
			<zValue>TRAIT_TUBERCULOSIS</zValue>
			<zValue>TRAIT_RABIES</zValue>
			<zValue>TRAIT_SEVERELY_ILL</zValue>
		</aeRemoveTraits>
	</Entry>
	<Entry>
		<zType>BONUS_EVENTOPTION_CHILD_FRAGILE</zType>
		<aeRandomTrait>
			<zValue>TRAIT_LEPROSY</zValue>
			<zValue>TRAIT_TYPHOID</zValue>
			<zValue>TRAIT_BUBONIC_PLAGUE</zValue>
		</aeRandomTrait>
		<aeAddTraits>
			<zValue>TRAIT_CRIPPLED</zValue>
		</aeAddTraits>
	</Entry>
	<Entry>
		<zType>BONUS_EVENTOPTION_CHILD_THE_PUPPIES_OPTION_2_CHARACTER_1</zType>
		<aeRandomTrait>
			<zValue>TRAIT_BUBONIC_PLAGUE</zValue>
			<zValue>TRAIT_INFLUENZA</zValue>
			<zValue>TRAIT_RABIES</zValue>
			<zValue>TRAIT_TUBERCULOSIS</zValue>			
		</aeRandomTrait>
	</Entry>
	<Entry>
		<zType>BONUS_EVENTOPTION_CHILD_THE_BAD_SEED_OPTION_1_CHARACTER_1</zType>
		<aeAddTraits>
			<zValue>TRAIT_WOUNDED</zValue>
			<zValue>TRAIT_EXILED</zValue>
		</aeAddTraits>
	</Entry>
	<Entry>
		<zType>BONUS_EVENTSTORY_TRAIT_A_FUNNY_FEELING_CHARACTER_2</zType>
		<aeAddTraits>
			<zValue>TRAIT_SEVERELY_ILL</zValue>
		</aeAddTraits>
	</Entry>
	<Entry>
		<zType>BONUS_EVENTOPTION_TRAIT_THE_PRICE_OPTION_0_CHARACTER_0</zType>
		<aeRemoveTraits>
			<zValue>TRAIT_SEVERELY_ILL</zValue>
			<zValue>TRAIT_BUBONIC_PLAGUE</zValue>
			<zValue>TRAIT_INFLUENZA</zValue>
			<zValue>TRAIT_RABIES</zValue>
			<zValue>TRAIT_TUBERCULOSIS</zValue>	
			<zValue>TRAIT_SMALLPOX</zValue>		
			<zValue>TRAIT_PNEUMONIA</zValue>			
		</aeRemoveTraits>
	</Entry>
	<Entry>
		<zType>BONUS_EVENTOPTION_TRAIT_THE_PRICE_OPTION_2_CHARACTER_0</zType>
		<aeRemoveTraits>
			<zValue>TRAIT_SEVERELY_ILL</zValue>
			<zValue>TRAIT_BUBONIC_PLAGUE</zValue>
			<zValue>TRAIT_INFLUENZA</zValue>
			<zValue>TRAIT_RABIES</zValue>
			<zValue>TRAIT_TUBERCULOSIS</zValue>	
			<zValue>TRAIT_SMALLPOX</zValue>	
			<zValue>TRAIT_PNEUMONIA</zValue>			
		</aeRemoveTraits>
	</Entry>
	<Entry>
		<zType>BONUS_EVENTOPTION_TRAIT_THE_MYSTIC_OPTION_0</zType>
		<Name>TEXT_BONUS_EVENTOPTION_TRAIT_THE_MYSTIC_OPTION_0</Name>
		<iLegitimacy>-2</iLegitimacy>
		<aeRemoveTraits>
			<zValue>TRAIT_PNEUMONIA</zValue>
			<zValue>TRAIT_INFLUENZA</zValue>
			<zValue>TRAIT_TYPHOID</zValue>
			<zValue>TRAIT_TUBERCULOSIS</zValue>
		</aeRemoveTraits>
		<AddCourtier>
			<Pair>
				<zIndex>COURTIER_MINISTER</zIndex>
				<zValue>GENDER_MALE</zValue>
			</Pair>
		</AddCourtier>
	</Entry>
	<Entry>
		<zType>BONUS_EVENTOPTION_TRAIT_THE_DOCTOR_OPTION_0</zType>
		<aeRemoveTraits>
			<zValue>TRAIT_SEVERELY_ILL</zValue>
			<zValue>TRAIT_TYPHOID</zValue>			
		</aeRemoveTraits>
		<aeBonuses>
			<zValue>BONUS_MONEY_LOSS_LARGE</zValue>
		</aeBonuses>
	</Entry>
	<Entry>
		<zType>BONUS_EVENTOPTION_TRAIT_DO_IT_YOURSELF_OPTION_2_CHARACTER_0</zType>
		<aeRemoveTraits>
			<zValue>TRAIT_SEVERELY_ILL</zValue>
			<zValue>TRAIT_TYPHOID</zValue>
		</aeRemoveTraits>
		<aeBonuses>
			<zValue>BONUS_XP_CHARACTER_SMALL</zValue>
		</aeBonuses>
	</Entry>
	<Entry>
		<zType>BONUS_EVENTOPTION_TRAIT_FULL_RECOVERY_OPTION_0_CHARACTER_0</zType>
		<aeRemoveTraits>
			<zValue>TRAIT_SEVERELY_ILL</zValue>
			<zValue>TRAIT_TYPHOID</zValue>
		</aeRemoveTraits>
		<aeBonuses>
			<zValue>BONUS_XP_CHARACTER_SMALL</zValue>
		</aeBonuses>
	</Entry>
	<Entry>
		<zType>BONUS_EVENTOPTION_TRAIT_PICTURE_OF_HEALTH_OPTION_0_CHARACTER_0</zType>
		<aeRemoveTraits>
			<zValue>TRAIT_SEVERELY_ILL</zValue>
			<zValue>TRAIT_MALARIA</zValue>
			<zValue>TRAIT_SMALLPOX</zValue>
			<zValue>TRAIT_BUBONIC_PLAGUE</zValue>
			<zValue>TRAIT_TYPHOID</zValue>
			<zValue>TRAIT_INFLUENZA</zValue>
			<zValue>TRAIT_PNEUMONIA</zValue>
			<zValue>TRAIT_TUBERCULOSIS</zValue>
		</aeRemoveTraits>
	</Entry>
	<Entry>
		<zType>BONUS_EVENTOPTION_RISE_AND_FALL_OPTION_0_CHARACTER_1</zType>
		<aeRandomTrait>
			<zValue>TRAIT_SEVERELY_ILL</zValue>
			<zValue>TRAIT_SMALLPOX</zValue>
			<zValue>TRAIT_MALARIA</zValue>	
		</aeRandomTrait>
		<aeAddTraits>
			<zValue>TRAIT_CRIPPLED</zValue>
		</aeAddTraits>
	</Entry>
	<Entry>
		<zType>BONUS_EVENTOPTION_LEGACY_OF_THE_PAW_OPTION_0_CHARACTER_0</zType>
		<bAbdicate>1</bAbdicate>
		<aeRandomTrait>
			<zValue>TRAIT_SEVERELY_ILL</zValue>
			<zValue>TRAIT_RABIES</zValue>
			<zValue>TRAIT_MALARIA</zValue>	
		</aeRandomTrait>
		<aeAddTraits>
			<zValue>TRAIT_CRIPPLED</zValue>
		</aeAddTraits>
		<aeRemoveTraits>
			<zValue>TRAIT_MONKEY_PAW</zValue>
		</aeRemoveTraits>
	</Entry>
	<Entry>
		<zType>BONUS_PAW_CURE_WISE</zType>
		<aeRemoveTraits>
			<zValue>TRAIT_SEVERELY_ILL</zValue>
			<zValue>TRAIT_RABIES</zValue>
			<zValue>TRAIT_MALARIA</zValue>
			<zValue>TRAIT_SMALLPOX</zValue>
			<zValue>TRAIT_BUBONIC_PLAGUE</zValue>
			<zValue>TRAIT_TYPHOID</zValue>
			<zValue>TRAIT_INFLUENZA</zValue>
			<zValue>TRAIT_LEPROSY</zValue>
			<zValue>TRAIT_PNEUMONIA</zValue>
			<zValue>TRAIT_TUBERCULOSIS</zValue>
		</aeRemoveTraits>
		<aeBonuses>
			<zValue>BONUS_XP_CHARACTER_LARGE</zValue>
		</aeBonuses>
	</Entry>
	<Entry>
		<zType>BONUS_EVENTOPTION_TRAIT_TAKING_ITS_TOLL_OPTION_0_CHARACTER_0</zType>
		<aeRandomTrait>
			<zValue>TRAIT_BUBONIC_PLAGUE</zValue>
			<zValue>TRAIT_TYPHOID</zValue>
			<zValue>TRAIT_LEPROSY</zValue>
			<zValue>TRAIT_PNEUMONIA</zValue>	
			<zValue>TRAIT_TUBERCULOSIS</zValue>			
		</aeRandomTrait>
		<aeAddTraits>
			<zValue>TRAIT_SEVERELY_ILL</zValue>
			<zValue>TRAIT_MISERABLE</zValue>
		</aeAddTraits>
	</Entry>
	<Entry>
		<zType>BONUS_PAW_CURE</zType>
		<aeRemoveTraits>
			<zValue>TRAIT_SEVERELY_ILL</zValue>
			<zValue>TRAIT_RABIES</zValue>
			<zValue>TRAIT_MALARIA</zValue>
			<zValue>TRAIT_SMALLPOX</zValue>
			<zValue>TRAIT_BUBONIC_PLAGUE</zValue>
			<zValue>TRAIT_TYPHOID</zValue>
			<zValue>TRAIT_INFLUENZA</zValue>
			<zValue>TRAIT_LEPROSY</zValue>
			<zValue>TRAIT_PNEUMONIA</zValue>
			<zValue>TRAIT_TUBERCULOSIS</zValue>
		</aeRemoveTraits>
	</Entry>
	<Entry>
		<zType>BONUS_EVENTSTORY_THE_POX_SPREADS_CHARACTER_0</zType>
		<aeAddTraits>
			<zValue>TRAIT_SMALLPOX</zValue>
		</aeAddTraits>
	</Entry>
	<Entry>
		<zType>BONUS_EVENTOPTION_DISHEARTENING_NEWS_OPTION_0_CHARACTER_0</zType>
		<aeRandomTrait>
			<zValue>TRAIT_BUBONIC_PLAGUE</zValue>
			<zValue>TRAIT_TYPHOID</zValue>
			<zValue>TRAIT_LEPROSY</zValue>
			<zValue>TRAIT_PNEUMONIA</zValue>	
			<zValue>TRAIT_TUBERCULOSIS</zValue>			
		</aeRandomTrait>
		<aeAddTraits>
			<zValue>TRAIT_SEVERELY_ILL</zValue>
		</aeAddTraits>
	</Entry>
	<Entry>
		<zType>BONUS_EVENTSTORY_SPOUSE_REVIVAL_CHARACTER_0</zType>
		<aiRatings>
			<Pair>
				<zIndex>RATING_COURAGE</zIndex>
				<iValue>1</iValue>
			</Pair>
		</aiRatings>
		<aeRemoveTraits>
			<zValue>TRAIT_SEVERELY_ILL</zValue>
			<zValue>TRAIT_RABIES</zValue>
			<zValue>TRAIT_MALARIA</zValue>
			<zValue>TRAIT_SMALLPOX</zValue>
			<zValue>TRAIT_BUBONIC_PLAGUE</zValue>
			<zValue>TRAIT_TYPHOID</zValue>
			<zValue>TRAIT_INFLUENZA</zValue>
			<zValue>TRAIT_LEPROSY</zValue>
			<zValue>TRAIT_PNEUMONIA</zValue>
			<zValue>TRAIT_TUBERCULOSIS</zValue>
		</aeRemoveTraits>
	</Entry>
</Root>

