<!-- Diseases Extended (© Revan© ) -->

<Root>
	<Entry>
		<zType>SUBJECT_HEALTHY</zType>
		<Class>SUBJECTCLASS_CHARACTER</Class>
		<TraitInvalid>
			<zValue>TRAIT_MALARIA</zValue>
			<zValue>TRAIT_SMALLPOX</zValue>
			<zValue>TRAIT_BUBONIC_PLAGUE</zValue>
			<zValue>TRAIT_TYPHOID</zValue>
			<zValue>TRAIT_INFLUENZA</zValue>
			<zValue>TRAIT_LEPROSY</zValue>
			<zValue>TRAIT_RABIES</zValue>
			<zValue>TRAIT_PNEUMONIA</zValue>
			<zValue>TRAIT_TUBERCULOSIS</zValue>
			<zValue>TRAIT_TRACHOMA</zValue>
			<zValue>TRAIT_SEVERELY_ILL</zValue>
		</TraitInvalid>
	</Entry>
</Root>
